loopstructuralvisualisation/_2d_viewer.py
loopstructuralvisualisation/_3d_viewer.py
loopstructuralvisualisation/__init__.py
loopstructuralvisualisation/_register_loop_ui.py
loopstructuralvisualisation/_rotation_angle.py
loopstructuralvisualisation/_stratigraphic_column.py
loopstructuralvisualisation/api.py
loopstructuralvisualisation/version.py
loopstructuralvisualisation/trame/__init__.py
loopstructuralvisualisation/trame/ui/vuetify3.py
loopstructuralvisualisation-0.1.17.dist-info/licenses/LICENSE
loopstructuralvisualisation-0.1.17.dist-info/METADATA
loopstructuralvisualisation-0.1.17.dist-info/WHEEL
loopstructuralvisualisation-0.1.17.dist-info/top_level.txt
loopstructuralvisualisation-0.1.17.dist-info/RECORD
