Metadata-Version: 2.4
Name: loopstructuralvisualisation
Version: 0.1.17
Summary: 3D geological modelling
Author-email: Lachlan Grose <lachlan.grose@monash.edu>
License: MIT
Project-URL: Documentation, https://Loop3d.org/LoopStructural/
Project-URL: Bug Tracker, https://github.com/loop3d/loopstructural-visualisation/issues
Project-URL: Source Code, https://github.com/loop3d/loopstructural-visualisation
Keywords: earth sciences,geology,3-D modelling,structural geology,uncertainty
Classifier: Development Status :: 5 - Production/Stable
Classifier: Intended Audience :: Science/Research
Classifier: Topic :: Scientific/Engineering :: Information Analysis
Classifier: License :: OSI Approved :: MIT License
Classifier: Operating System :: Microsoft :: Windows
Classifier: Operating System :: POSIX
Classifier: Operating System :: MacOS
Classifier: Programming Language :: Python :: 3.8
Classifier: Programming Language :: Python :: 3.9
Classifier: Programming Language :: Python :: 3.10
Classifier: Programming Language :: Python :: 3.11
Classifier: Programming Language :: Python :: 3.12
Requires-Python: >=3.9
License-File: LICENSE
Requires-Dist: numpy>=1.18
Requires-Dist: pyvista>=0.42
Requires-Dist: LoopStructural>=1.6.17
Provides-Extra: jupyter
Requires-Dist: pyvista[jupyter]; extra == "jupyter"
Provides-Extra: all
Requires-Dist: pyvista[all]; extra == "all"
Dynamic: license-file
